RW/DNS.py
RW/Elasticsearch.py
RW/GitLab.py
RW/Grafana.py
RW/HTTP.py
RW/Jira.py
RW/Kubectl.py
RW/MSTeams.py
RW/MyTest.py
RW/Opsgenie.py
RW/PagerDuty.py
RW/Pingdom.py
RW/Remote.py
RW/Rocketchat.py
RW/Slack.py
RW/WebInspector.py
RW/__init__.py
RW/restclient.py
RW/AWS/Billing.py
RW/AWS/CloudFormation.py
RW/AWS/CloudWatch.py
RW/AWS/EC2.py
RW/AWS/S3.py
RW/AWS/__init__.py
RW/AWS/mixins/AWSAuthenticationMixin.py
RW/AWS/mixins/__init__.py
RW/AWS/robot_tests/billing.robot
RW/AWS/robot_tests/cloudformation.robot
RW/AWS/robot_tests/cloudwatch.robot
RW/AWS/robot_tests/cloudwatchlinks.robot
RW/AWS/robot_tests/combination.robot
RW/AWS/robot_tests/ec2.robot
RW/AWS/robot_tests/s3.robot
RW/AWS/robot_tests/test_queries.py
RW/AWS/strategies/GetClientStrategy.py
RW/AWS/strategies/RoleGetClientStrategy.py
RW/AWS/strategies/UserGetClientStrategy.py
RW/AWS/strategies/__init__.py
RW/ArgoCD/__init__.py
RW/ArgoCD/argocd.py
RW/Artifactory/Artifactory.py
RW/Artifactory/__init__.py
RW/Artifactory/robot_tests/health.robot
RW/CertManager/__init__.py
RW/CertManager/cert_manager.py
RW/CertManager/robot_tests/certs.robot
RW/Chat/__init__.py
RW/Chat/robot_tests/notify_multi.robot
RW/Chat/strategies/ChatProviderStrategy.py
RW/Chat/strategies/DiscordChatProviderStrategy.py
RW/Chat/strategies/GoogleChatProviderStrategy.py
RW/Chat/strategies/RocketChatProviderStrategy.py
RW/Chat/strategies/SlackChatProviderStrategy.py
RW/Chat/strategies/__init__.py
RW/Curl/Curl.py
RW/Curl/__init__.py
RW/Datadog/__init__.py
RW/Datadog/datadog.py
RW/Discord/Discord.py
RW/Discord/__init__.py
RW/Discord/robot_tests/send.robot
RW/GCP/Chat.py
RW/GCP/GCloudCLI.py
RW/GCP/OpsSuite.py
RW/GCP/ServiceHealth.py
RW/GCP/__init__.py
RW/GCP/robot_tests/chat.robot
RW/GCP/robot_tests/opssuite.robot
RW/GCP/robot_tests/servicehealth.robot
RW/GitHub/Actions.py
RW/GitHub/Status.py
RW/GitHub/__init__.py
RW/GitHub/robot_tests/actions.robot
RW/GitHub/robot_tests/status.robot
RW/HashiCorp/Vault.py
RW/HashiCorp/__init__.py
runwhen_public_keywords-0.0.15.dist-info/LICENSE
runwhen_public_keywords-0.0.15.dist-info/METADATA
runwhen_public_keywords-0.0.15.dist-info/WHEEL
runwhen_public_keywords-0.0.15.dist-info/top_level.txt
runwhen_public_keywords-0.0.15.dist-info/RECORD
